nanowireauthenticator
