Metadata-Version: 1.0
Name: jupyterhub-nanowireauthenticator
Version: 0.0.3
Summary: Nanowire Authenticator for JupyterHub
Home-page: https://github.com/spotlightdata/jupyterhub-nanowireauthenticator
Author: Jonathan Balls
Author-email: jonathan@spotlightdata.co.uk
License: 3 Clause BSD
Platform: UNKNOWN
